pyDatalog/Aggregate.py
pyDatalog/Logic.py
pyDatalog/UserList.py
pyDatalog/__init__.py
pyDatalog/doc.py
pyDatalog/pyDatalog.py
pyDatalog/pyEngine.cp37-win_amd64.pyd
pyDatalog/pyEngine.py
pyDatalog/pyParser.py
pyDatalog/util.py
pyDatalog/version.py
pyDatalog/examples/Mongo.py
pyDatalog/examples/SQLAlchemy.py
pyDatalog/examples/__init__.py
pyDatalog/examples/console.py
pyDatalog/examples/datalog.py
pyDatalog/examples/graph.py
pyDatalog/examples/hashtag.py
pyDatalog/examples/hashtag_optimized.py
pyDatalog/examples/multiModel.py
pyDatalog/examples/python.py
pyDatalog/examples/queens.py
pyDatalog/examples/queens_N.py
pyDatalog/examples/test.py
pyDatalog/examples/test_of_performance.py
pyDatalog/examples/threadSafe.py
pyDatalog/examples/tutorial.py
pyDatalog-0.17.4.dist-info/LICENCE
pyDatalog-0.17.4.dist-info/METADATA
pyDatalog-0.17.4.dist-info/WHEEL
pyDatalog-0.17.4.dist-info/top_level.txt
pyDatalog-0.17.4.dist-info/RECORD
