Metadata-Version: 2.1
Name: pyDatalog
Version: 0.17.4
Summary: A pure-python implementation of Datalog, a truly declarative language derived from Prolog.
Home-page: https://sites.google.com/site/pydatalog/
Author: Pierre Carbonnelle
Author-email: pierre.carbonnelle@gmail.com
License: UNKNOWN
Download-URL: http://pypi.python.org/pypi?name=pyDatalog&:action=display
Keywords: prolog,logic programming,database,SQL,data integration,expert system,AI
Platform: UNKNOWN
Classifier: Programming Language :: Python
Classifier: Programming Language :: Python :: 2.7
Classifier: Programming Language :: Python :: 3
Classifier: Programming Language :: Prolog
Classifier: Development Status :: 4 - Beta
Classifier: Environment :: Other Environment
Classifier: Intended Audience :: Developers
Classifier: Intended Audience :: Education
Classifier: Topic :: Database
Classifier: Topic :: Database :: Database Engines/Servers
Classifier: License :: OSI Approved :: GNU Library or Lesser General Public License (LGPL)
Classifier: Operating System :: OS Independent
Classifier: Topic :: Software Development :: Libraries :: Python Modules
Classifier: Topic :: Scientific/Engineering :: Artificial Intelligence
License-File: LICENCE
